MANIFEST.in
README.md
requirements.txt
setup.py
utcs_ssh.py
utcs_ssh.egg-info/PKG-INFO
utcs_ssh.egg-info/SOURCES.txt
utcs_ssh.egg-info/dependency_links.txt
utcs_ssh.egg-info/entry_points.txt
utcs_ssh.egg-info/requires.txt
utcs_ssh.egg-info/top_level.txt