Metadata-Version: 2.1
Name: utcs-ssh
Version: 0.0.1
Summary: A CLI tool to make it easier to access the best UTCS lab machines
Author: Samuel Gunter
Author-email: sgunter@utexas.edu
